verilog/fulladder/fadder.v
// Define a 1-bit full adder
module fulladd(sum, c_out, a, b, c_in);
    output sum, c_out;
    input a, b, c_in;
    
    // Internal nets
    wire s1, c1, c2;

    // Logic using operators
    assign s1 = a ^ b;          // XOR for a and b
    assign c1 = a & b;          // AND for a and b
    assign sum = s1 ^ c_in;     // XOR for sum
    assign c2 = s1 & c_in;      // AND for s1 and c_in
    assign c_out = c1 | c2;     // OR for carry out
endmodule

// Verilog Description for 4-bit Ripple Carry Full Adder
// Define a 4-bit full adder
module fulladd4(sum, c_out, a, b, c_in);
 output [3:0] sum;
 output c_out;
 input[3:0] a, b;
 input c_in;
 // Internal nets
 wire c1, c2, c3;
 // Instantiate four 1-bit full adders.
 fulladd fa0(sum[0], c1, a[0], b[0], c_in);
 fulladd fa1(sum[1], c2, a[1], b[1], c1);
 fulladd fa2(sum[2], c3, a[2], b[2], c2);
 fulladd fa3(sum[3], c_out, a[3], b[3], c3);
endmodule

verilog/fulladder/fadder.tb.v
`timescale 1ns / 1ps

module tb_fulladd4; // Testbench for 4-bit full adder

    // Testbench signals
    reg [3:0] a;      // 4-bit input a
    reg [3:0] b;      // 4-bit input b
    reg c_in;        // Carry input
    wire [3:0] sum;   // 4-bit sum output
    wire c_out;      // Carry output

    // Instantiate the 4-bit full adder
    fulladd4 uut (
        .sum(sum),
        .c_out(c_out),
        .a(a),
        .b(b),
        .c_in(c_in)
    );

    // Task to apply test cases
    task apply_test(input [3:0] a_test, input [3:0] b_test, input c_in_test);
        begin
            a = a_test;
            b = b_test;
            c_in = c_in_test;
            #10; // Wait for 10 time units
            // Display results
            $display("A = %b, B = %b, Cin = %b | Sum = %b, Cout = %b", a, b, c_in, sum, c_out);
        end
    endtask

    // Test procedure
    initial begin
        // Initialize waveform dump
        $dumpfile("fadder.vcd"); // Specify the name of the VCD file
        $dumpvars(0, tb_fulladd4);  // Dump all variables in the testbench

        // Display header
        $display("A      B      Cin  |  Sum   Cout");
        $display("-----------------------------------");

        // Apply test cases
        apply_test(4'b0000, 4'b0000, 0); // 0 + 0 + 0
        apply_test(4'b0001, 4'b0001, 0); // 1 + 1 + 0
        apply_test(4'b0010, 4'b0011, 0); // 2 + 3 + 0
        apply_test(4'b0111, 4'b0001, 0); // 7 + 1 + 0
        apply_test(4'b1111, 4'b0001, 0); // 15 + 1 + 0
        apply_test(4'b1111, 4'b1111, 1); // 15 + 15 + 1
        apply_test(4'b1010, 4'b0101, 1); // 10 + 5 + 1
        apply_test(4'b1100, 4'b0011, 1); // 12 + 3 + 1

        // End simulation
        $finish;
    end
endmodule

verilog/fulladder/fadder.vcd
$date
	Thu Nov 21 21:49:04 2024
$end
$version
	Icarus Verilog
$end
$timescale
	1ps
$end
$scope module tb_fulladd4 $end
$var wire 4 ! sum [3:0] $end
$var wire 1 " c_out $end
$var reg 4 # a [3:0] $end
$var reg 4 $ b [3:0] $end
$var reg 1 % c_in $end
$scope module uut $end
$var wire 4 & a [3:0] $end
$var wire 4 ' b [3:0] $end
$var wire 1 % c_in $end
$var wire 4 ( sum [3:0] $end
$var wire 1 " c_out $end
$var wire 1 ) c3 $end
$var wire 1 * c2 $end
$var wire 1 + c1 $end
$scope module fa0 $end
$var wire 1 , a $end
$var wire 1 - b $end
$var wire 1 . c1 $end
$var wire 1 / c2 $end
$var wire 1 % c_in $end
$var wire 1 + c_out $end
$var wire 1 0 s1 $end
$var wire 1 1 sum $end
$upscope $end
$scope module fa1 $end
$var wire 1 2 a $end
$var wire 1 3 b $end
$var wire 1 4 c1 $end
$var wire 1 5 c2 $end
$var wire 1 + c_in $end
$var wire 1 * c_out $end
$var wire 1 6 s1 $end
$var wire 1 7 sum $end
$upscope $end
$scope module fa2 $end
$var wire 1 8 a $end
$var wire 1 9 b $end
$var wire 1 : c1 $end
$var wire 1 ; c2 $end
$var wire 1 * c_in $end
$var wire 1 ) c_out $end
$var wire 1 < s1 $end
$var wire 1 = sum $end
$upscope $end
$scope module fa3 $end
$var wire 1 > a $end
$var wire 1 ? b $end
$var wire 1 @ c1 $end
$var wire 1 A c2 $end
$var wire 1 ) c_in $end
$var wire 1 " c_out $end
$var wire 1 B s1 $end
$var wire 1 C sum $end
$upscope $end
$upscope $end
$scope task apply_test $end
$var reg 4 D a_test [3:0] $end
$var reg 4 E b_test [3:0] $end
$var reg 1 F c_in_test $end
$upscope $end
$upscope $end
$enddefinitions $end
#0
$dumpvars
0F
b0 E
b0 D
0C
0B
0A
0@
0?
0>
0=
0<
0;
0:
09
08
07
06
05
04
03
02
01
00
0/
0.
0-
0,
0+
0*
0)
b0 (
b0 '
b0 &
0%
b0 $
b0 #
0"
b0 !
$end
#10000
b10 !
b10 (
17
1+
1.
1-
1,
b1 $
b1 '
b1 #
b1 &
b1 E
b1 D
#20000
07
1=
b101 !
b101 (
11
0+
1*
10
0.
14
13
0,
12
b11 $
b11 '
b10 #
b10 &
b11 E
b10 D
#30000
1C
1)
15
1*
01
1+
b1000 !
b1000 (
0=
1;
16
04
00
1.
1<
03
1,
18
b1 $
b1 '
b111 #
b111 &
b1 E
b111 D
#40000
1"
b0 !
b0 (
0C
1A
1B
1>
b1111 #
b1111 &
b1111 D
#50000
17
05
1=
0;
1C
0A
06
14
0<
1:
0B
1@
b1111 !
b1111 (
11
13
19
1?
1%
b1111 $
b1111 '
1F
b1111 E
#60000
07
15
0C
1A
1*
1"
01
1/
1+
b0 !
b0 (
0=
1;
1)
16
04
1B
0@
10
0.
1<
0:
03
0?
0,
08
b101 $
b101 '
b1010 #
b1010 &
b101 E
b1010 D
#70000
13
09
02
18
b11 $
b11 '
b1100 #
b1100 &
b11 E
b1100 D
