verilog/not/pmos-nmos/not.v
`timescale 1ns / 1ps

module not_gate (
    input wire a,      // Input signal a
    output wire out    // Output signal
);

    // Power supply connections
    supply1 vdd;    // VDD (positive supply voltage) = 1
    supply0 gnd;    // GND (ground) = 0

    // PMOS transistor with 6ns delay
    pmos #(6) p1(out, vdd, a);  // pmos(output, power, input)

    // NMOS transistor with 4ns delay
    nmos #(4) n1(out, gnd, a);  // nmos(output, ground, input)

endmodule

// Truth table for PMOS and NMOS transistors in NOT gate:
//
// Input (a) | PMOS (p1) | NMOS (n1) | Output (out)
// ---------|-----------|-----------|-------------
//    0     |    ON     |    OFF    |     1
//    1     |    OFF    |    ON     |     0
//
// When input is 0:
// - PMOS is ON, connecting output to VDD (1)
// - NMOS is OFF, not affecting the output
// Result: Output is pulled up to 1
//
// When input is 1:
// - PMOS is OFF, not affecting the output
// - NMOS is ON, connecting output to GND (0)
// Result: Output is pulled down to 0

verilog/not/pmos-nmos/not.tb.v
`timescale 1ns / 1ps  // Define the time scale for the simulation

module tb_not;  // Testbench module

    // Declare testbench signals
    reg a;            // Input signal for the NOT gate
    wire out;         // Output signal from the NOT gate

    // Instantiate the NOT gate
    not_gate uut (
        .a(a),      // Connect input a
        .out(out)     // Connect output
    );

    // Add VCD file generation
    initial begin
        $dumpfile("not.vcd");  // Create a VCD file named "not.vcd"
        $dumpvars(0, tb_not);  // Dump all variables in the testbench
    end

    // Test procedure
    initial begin
        // Display the header
        $display("Time(ns) | Input A | Output");
        $monitor("%0t | %b     | %b", $time, a, out);

        // Test case 1: A = 0
        a = 0;  // Apply input A = 0
        #5;     // Wait for 5 ns

        // Test case 2: A = 1
        a = 1;  // Apply input A = 1
        #5;     // Wait for 5 ns

        // Test case 3: A = 0
        a = 0;  // Apply input A = 0
        #5;     // Wait for 5 ns

        // Test case 4: A = 1
        a = 1;  // Apply input A = 1
        #5;     // Wait for 5 ns

        // Test case 5: A = 0
        a = 0;  // Apply input A = 0
        #5;     // Wait for 5 ns

        // Test case 6: A = 1
        a = 1;  // Apply input A = 1
        #5;     // Wait for 5 ns

        // End the simulation
        $finish;
    end

endmodule

verilog/not/pmos-nmos/not.vcd
$date
	Tue Oct 15 16:01:30 2024
$end
$version
	Icarus Verilog
$end
$timescale
	1ps
$end
$scope module tb_not $end
$var wire 1 ! out $end
$var reg 1 " a $end
$scope module uut $end
$var wire 1 " a $end
$var wire 1 # gnd $end
$var wire 1 ! out $end
$var wire 1 $ vdd $end
$upscope $end
$upscope $end
$enddefinitions $end
$comment Show the parameter values. $end
$dumpall
$end
#0
$dumpvars
1$
0#
0"
x!
$end
#4000
x!
#5000
1"
#9000
x!
#10000
0"
#14000
x!
#15000
1"
#19000
x!
#20000
0"
#24000
x!
#25000
1"
#29000
x!
